randomalphabets/__init__.py
randomalphabets/randomalphabets.py
randomalphabets-0.1.0.dist-info/WHEEL
randomalphabets-0.1.0.dist-info/METADATA
randomalphabets-0.1.0.dist-info/RECORD
