Metadata-Version: 2.1
Name: randomalphabets
Version: 0.1.0
Summary: Generate a string of n random alphabets.
Author: Ashin K Ajay
Author-email: ashinkajayclt@gmail.com
Requires-Python: >=3.8,<4.0
Classifier: Programming Language :: Python :: 3
Classifier: Programming Language :: Python :: 3.8
Classifier: Programming Language :: Python :: 3.9
